LICENSE
MANIFEST.in
README.rst
setup.py
polist/__init__.py
polist/polist.py
polist/test.py
polist.egg-info/PKG-INFO
polist.egg-info/SOURCES.txt
polist.egg-info/dependency_links.txt
polist.egg-info/top_level.txt