Metadata-Version: 1.1
Name: polist
Version: 0.0.2
Summary: polist, partially ordered list
Home-page: https://github.com/shoz/polist
Author: Shoji Ihara
Author-email: shoji.ihara@gmail.com
License: MIT
Keywords: data structure list topological sort
Platform: UNKNOWN
Classifier: Development Status :: 1 - Planning
Classifier: Intended Audience :: Developers
Classifier: Intended Audience :: Science/Research
Classifier: License :: OSI Approved :: MIT License
